CHANGES.txt
COPYRIGHT.txt
CREDITS.txt
LICENSE.txt
MANIFEST.in
README.txt
bootstrap.py
buildout.cfg
setup.py
src/hurry/__init__.py
src/hurry.jqueryui.egg-info/PKG-INFO
src/hurry.jqueryui.egg-info/SOURCES.txt
src/hurry.jqueryui.egg-info/dependency_links.txt
src/hurry.jqueryui.egg-info/entry_points.txt
src/hurry.jqueryui.egg-info/namespace_packages.txt
src/hurry.jqueryui.egg-info/not-zip-safe
src/hurry.jqueryui.egg-info/requires.txt
src/hurry.jqueryui.egg-info/top_level.txt
src/hurry/jqueryui/__init__.py
src/hurry/jqueryui/_themes.py
src/hurry/jqueryui/jqueryui.txt
src/hurry/jqueryui/prepare.py
src/hurry/jqueryui/tests.py
src/hurry/jqueryui/jqueryui-build/jquery-ui.js
src/hurry/jqueryui/jqueryui-build/jquery-ui.min.js
src/hurry/jqueryui/jqueryui-themes/base/jquery-ui.css
src/hurry/jqueryui/jqueryui-themes/base/jquery.ui.accordion.css
src/hurry/jqueryui/jqueryui-themes/base/jquery.ui.all.css
src/hurry/jqueryui/jqueryui-themes/base/jquery.ui.autocomplete.css
src/hurry/jqueryui/jqueryui-themes/base/jquery.ui.base.css
src/hurry/jqueryui/jqueryui-themes/base/jquery.ui.button.css
src/hurry/jqueryui/jqueryui-themes/base/jquery.ui.core.css
src/hurry/jqueryui/jqueryui-themes/base/jquery.ui.datepicker.css
src/hurry/jqueryui/jqueryui-themes/base/jquery.ui.dialog.css
src/hurry/jqueryui/jqueryui-themes/base/jquery.ui.progressbar.css
src/hurry/jqueryui/jqueryui-themes/base/jquery.ui.resizable.css
src/hurry/jqueryui/jqueryui-themes/base/jquery.ui.selectable.css
src/hurry/jqueryui/jqueryui-themes/base/jquery.ui.slider.css
src/hurry/jqueryui/jqueryui-themes/base/jquery.ui.tabs.css
src/hurry/jqueryui/jqueryui-themes/base/jquery.ui.theme.css
src/hurry/jqueryui/jqueryui-themes/base/images/ui-bg_flat_0_aaaaaa_40x100.png
src/hurry/jqueryui/jqueryui-themes/base/images/ui-bg_flat_75_ffffff_40x100.png
src/hurry/jqueryui/jqueryui-themes/base/images/ui-bg_glass_55_fbf9ee_1x400.png
src/hurry/jqueryui/jqueryui-themes/base/images/ui-bg_glass_65_ffffff_1x400.png
src/hurry/jqueryui/jqueryui-themes/base/images/ui-bg_glass_75_dadada_1x400.png
src/hurry/jqueryui/jqueryui-themes/base/images/ui-bg_glass_75_e6e6e6_1x400.png
src/hurry/jqueryui/jqueryui-themes/base/images/ui-bg_glass_95_fef1ec_1x400.png
src/hurry/jqueryui/jqueryui-themes/base/images/ui-bg_highlight-soft_75_cccccc_1x100.png
