Metadata-Version: 1.0
Name: hurry.jqueryui
Version: 1.8.5.1
Summary: hurry.resource style resources for jQuery UI.
Home-page: UNKNOWN
Author: Martijn Faassen
Author-email: faassen@startifact.com
License: ZPL 2.1
Platform: UNKNOWN
